cascade_settings/__init__.py
cascade_settings-0.1.0.dist-info/METADATA
cascade_settings-0.1.0.dist-info/WHEEL
cascade_settings-0.1.0.dist-info/top_level.txt
cascade_settings-0.1.0.dist-info/RECORD
