Metadata-Version: 2.1
Name: cascade-settings
Version: 0.1.0
Summary: UNKNOWN
Home-page: UNKNOWN
Author: Szymon Zareba
Author-email: szymon.zareba@alphamoon.ai
License: UNKNOWN
Platform: UNKNOWN
Requires-Python: >=3.6.0
Requires-Dist: simple-settings
